{
  "shapes": [
    {
      "shape_type": "polygon", 
      "points": [
        [
          286.3013698630137, 
          279.75342465753425
        ], 
        [
          116.43835616438356, 
          368.79452054794524
        ], 
        [
          1.36986301369863, 
          363.3150684931507
        ], 
        [
          1.36986301369863, 
          478.3835616438356
        ], 
        [
          635.6164383561644, 
          477.013698630137
        ], 
        [
          635.6164383561644, 
          443.45205479452056
        ], 
        [
          409.5890410958904, 
          311.94520547945206
        ], 
        [
          362.32876712328766, 
          307.1506849315069
        ], 
        [
          360.2739726027397, 
          293.45205479452056
        ], 
        [
          371.9178082191781, 
          290.7123287671233
        ], 
        [
          352.05479452054794, 
          277.013698630137
        ]
      ], 
      "flags": {}, 
      "group_id": null, 
      "label": "footpath"
    }
  ], 
  "imagePath": "../Dataset/163.png", 
  "flags": {}, 
  "version": "4.5.7", 
  "imageData": null, 
  "imageWidth": 640, 
  "imageHeight": 480
}