{
  "shapes": [
    {
      "shape_type": "polygon", 
      "points": [
        [
          1.0, 
          338.2352941176471
        ], 
        [
          301.0, 
          275.4901960784314
        ], 
        [
          360.3137254901961, 
          275.0
        ], 
        [
          434.3333333333333, 
          313.72549019607845
        ], 
        [
          639, 
          404
        ], 
        [
          639, 
          477
        ], 
        [
          1.9803921568627416, 
          475.98039215686276
        ]
      ], 
      "flags": {}, 
      "group_id": null, 
      "label": "footpath"
    }
  ], 
  "imagePath": "../Dataset/51.png", 
  "flags": {}, 
  "version": "4.5.7", 
  "imageData": null, 
  "imageWidth": 640, 
  "imageHeight": 480
}