{
  "shapes": [
    {
      "shape_type": "polygon", 
      "points": [
        [
          236.5, 
          284.83333333333337
        ], 
        [
          396.22222222222223, 
          285.52777777777777
        ], 
        [
          455.94444444444446, 
          314.69444444444446
        ], 
        [
          517.75, 
          317.47222222222223
        ], 
        [
          527.4722222222223, 
          339.69444444444446
        ], 
        [
          635.8055555555555, 
          389.69444444444446
        ], 
        [
          638.5833333333334, 
          478.58333333333337
        ], 
        [
          0.38888888888888884, 
          477.8888888888889
        ], 
        [
          3.166666666666667, 
          350.80555555555554
        ], 
        [
          136.5, 
          314.0
        ], 
        [
          132.33333333333334, 
          311.22222222222223
        ], 
        [
          149.69444444444446, 
          302.8888888888889
        ], 
        [
          173.30555555555557, 
          299.4166666666667
        ], 
        [
          189.97222222222223, 
          291.77777777777777
        ]
      ], 
      "flags": {}, 
      "group_id": null, 
      "label": "footpath"
    }
  ], 
  "imagePath": "../Dataset/30.png", 
  "flags": {}, 
  "version": "4.5.7", 
  "imageData": null, 
  "imageWidth": 640, 
  "imageHeight": 480
}